{"total":30,"pageSize":5,"pageCount":6,"data":[{"title":"25【学习总结】从模拟strcpy和strlen函数中总结的要点","slug":"25【学习总结】从模拟strcpy和strlen函数中总结的要点","date":"2018-10-28T13:17:06.000Z","updated":"2018-10-28T13:20:24.647Z","comments":true,"path":"api/articles/25【学习总结】从模拟strcpy和strlen函数中总结的要点.json","excerpt":"<h2 id=\"前言\"><a href=\"#前言\" class=\"headerlink\" title=\"前言\"></a>前言</h2><p>不只能输出正确，还要通过一些细节让程序更加健壮！</p>\n<p>资料：《高质量C++/C编程》</p>","keywords":null,"cover":"https://wx3.sinaimg.cn/mw690/006wR0dcly1fwo1u6tk8zj31by16yjyi.jpg","content":null,"text":"前言不只能输出正确，还要通过一些细节让程序更加健壮！资料：《高质量C++/C编程》模拟实现strcpy和strlen函数的几个注意点在模拟实现函数的过程中，不只要只实现个功能，还要注重如何让代码更加健壮！先来给出code，下面再详细解释：1<br>2<br>3<br>4<br>5","link":"","raw":null,"photos":[],"categories":[{"name":"学习总结","slug":"学习总结","count":5,"path":"api/categories/学习总结.json"}],"tags":[{"name":"C语言","slug":"C语言","count":19,"path":"api/tags/C语言.json"},{"name":"学习总结","slug":"学习总结","count":9,"path":"api/tags/学习总结.json"}]},{"title":"24【学习总结】const修饰的是谁","slug":"24【学习总结】const修饰的是谁","date":"2018-10-28T13:12:44.000Z","updated":"2018-10-28T13:15:21.322Z","comments":true,"path":"api/articles/24【学习总结】const修饰的是谁.json","excerpt":"<h2 id=\"前言\"><a href=\"#前言\" class=\"headerlink\" title=\"前言\"></a>前言</h2><p>const : 我是谁，我在哪，我要干甚？ </p>","keywords":null,"cover":null,"content":null,"text":"前言const : 我是谁，我在哪，我要干甚？ 正文const修饰的谁？要在编程中多正确的使用const来使程序变得更加健壮。《高质量C++/C编程指南》const是修饰谁?1<br>2<br>3<br>4<br>5<br>6<br>7<br>8<br>9<br>10<br>11","link":"","raw":null,"photos":[],"categories":[{"name":"学习总结","slug":"学习总结","count":5,"path":"api/categories/学习总结.json"}],"tags":[{"name":"C语言","slug":"C语言","count":19,"path":"api/tags/C语言.json"},{"name":"学习总结","slug":"学习总结","count":9,"path":"api/tags/学习总结.json"}]},{"title":"23【学习总结】二分查找","slug":"23【学习总结】二分查找","date":"2018-10-27T14:04:22.000Z","updated":"2018-10-27T14:09:15.393Z","comments":true,"path":"api/articles/23【学习总结】二分查找.json","excerpt":"<h2 id=\"前言\"><a href=\"#前言\" class=\"headerlink\" title=\"前言\"></a>前言</h2><p>笔记参考：极客时间|数据结构与算法之美</p>\n<p>之前在bilibili看到一个有趣的视频，关于二分查找的。<a href=\"https://www.bilibili.com/video/av15833965\" target=\"_blank\" rel=\"noopener\">戳我看这个有趣的视频</a></p>\n<h2 id=\"目录\"><a href=\"#目录\" class=\"headerlink\" title=\"目录\"></a>目录</h2><h3 id=\"1-二分思想\"><a href=\"#1-二分思想\" class=\"headerlink\" title=\"1. 二分思想\"></a>1. 二分思想</h3><h3 id=\"2-递归和非递归实现\"><a href=\"#2-递归和非递归实现\" class=\"headerlink\" title=\"2. 递归和非递归实现\"></a>2. 递归和非递归实现</h3><h3 id=\"3-时间复杂度\"><a href=\"#3-时间复杂度\" class=\"headerlink\" title=\"3. 时间复杂度\"></a>3. 时间复杂度</h3><h3 id=\"4-局限性\"><a href=\"#4-局限性\" class=\"headerlink\" title=\"4. 局限性\"></a>4. 局限性</h3><h3 id=\"5-变体问题\"><a href=\"#5-变体问题\" class=\"headerlink\" title=\"5. 变体问题\"></a>5. 变体问题</h3>","keywords":null,"cover":null,"content":null,"text":"前言笔记参考：极客时间|数据结构与算法之美之前在bilibili看到一个有趣的视频，关于二分查找的。戳我看这个有趣的视频目录1. 二分思想2. 递归和非递归实现3. 时间复杂度4. 局限性5. 变体问题正文1. 二分思想就如上面视频中的栗子，猜数字游戏，如果从头开始一个一个的猜是","link":"","raw":null,"photos":[],"categories":[{"name":"学习总结","slug":"学习总结","count":5,"path":"api/categories/学习总结.json"}],"tags":[{"name":"学习总结","slug":"学习总结","count":9,"path":"api/tags/学习总结.json"},{"name":"算法","slug":"算法","count":2,"path":"api/tags/算法.json"}]},{"title":"22【练习】经典递归问题","slug":"22【练习】经典递归问题","date":"2018-10-26T08:50:45.000Z","updated":"2018-10-27T14:10:00.768Z","comments":true,"path":"api/articles/22【练习】经典递归问题.json","excerpt":"<h2 id=\"前言\"><a href=\"#前言\" class=\"headerlink\" title=\"前言\"></a>前言</h2><p>7个经典递归问题练习。</p>","keywords":null,"cover":null,"content":null,"text":"前言7个经典递归问题练习。正文在n个球中，任意取m个(不放回)，求有多少种取法1<br>2<br>3<br>4<br>5<br>6<br>7<br>8<br>9<br>10<br>11<br>12<br>13<br>14<br>15<br>16<br>17<br>18<br>19","link":"","raw":null,"photos":[],"categories":[{"name":"练习","slug":"练习","count":9,"path":"api/categories/练习.json"}],"tags":[{"name":"练习","slug":"练习","count":10,"path":"api/tags/练习.json"},{"name":"递归","slug":"递归","count":1,"path":"api/tags/递归.json"},{"name":"算法","slug":"算法","count":2,"path":"api/tags/算法.json"}]},{"title":"21【学习总结】递归","slug":"21【学习总结】递归","date":"2018-10-23T05:30:28.000Z","updated":"2018-10-27T14:10:44.646Z","comments":true,"path":"api/articles/21【学习总结】递归.json","excerpt":"<h2 id=\"前言\"><a href=\"#前言\" class=\"headerlink\" title=\"前言\"></a>前言</h2><p>笔记参考：极客时间|数据结构与算法之美</p>\n<h2 id=\"目录\"><a href=\"#目录\" class=\"headerlink\" title=\"目录\"></a>目录</h2><h3 id=\"1-如何理解递归\"><a href=\"#1-如何理解递归\" class=\"headerlink\" title=\"1. 如何理解递归\"></a>1. 如何理解递归</h3><h3 id=\"2-递归需要满足的条件\"><a href=\"#2-递归需要满足的条件\" class=\"headerlink\" title=\"2. 递归需要满足的条件\"></a>2. 递归需要满足的条件</h3><h3 id=\"3-递归代码的实现\"><a href=\"#3-递归代码的实现\" class=\"headerlink\" title=\"3. 递归代码的实现\"></a>3. 递归代码的实现</h3><h3 id=\"4-栈溢出！\"><a href=\"#4-栈溢出！\" class=\"headerlink\" title=\"4. 栈溢出！\"></a>4. 栈溢出！</h3><h3 id=\"5-重复计算！\"><a href=\"#5-重复计算！\" class=\"headerlink\" title=\"5. 重复计算！\"></a>5. 重复计算！</h3><h3 id=\"6-递归代码-gt-非递归代码\"><a href=\"#6-递归代码-gt-非递归代码\" class=\"headerlink\" title=\"6. 递归代码-&gt;非递归代码\"></a>6. 递归代码-&gt;非递归代码</h3>","keywords":null,"cover":"https://static001.geekbang.org/resource/image/e7/bf/e7e778994e90265344f6ac9da39e01bf.jpg","content":null,"text":"前言笔记参考：极客时间|数据结构与算法之美目录1. 如何理解递归2. 递归需要满足的条件3. 递归代码的实现4. 栈溢出！5. 重复计算！6. 递归代码-&gt;非递归代码递归1. 如何理解递归例：领导分配给你一个任务量为n的任务，你做了一部分，然后把剩下的n-1分配给别人，别人","link":"","raw":null,"photos":[],"categories":[{"name":"学习总结","slug":"学习总结","count":5,"path":"api/categories/学习总结.json"}],"tags":[{"name":"C语言","slug":"C语言","count":19,"path":"api/tags/C语言.json"},{"name":"学习总结","slug":"学习总结","count":9,"path":"api/tags/学习总结.json"}]}]}